{"type": "Feature", "properties": {"type": "node", "id": 877621131, "tags": {"amenity": "bicycle_rental", "capacity": "18", "name": "e.motion / Centro Santa Chiara", "network": "E.Motion", "operator": "Provincia di Trento", "website": "http://www.provincia.tn.it/bikesharing"}}, "geometry": {"type": "Point", "coordinates": [11.1238432, 46.0634049]}}