{"type": "Feature", "properties": {"type": "node", "id": 4745380978, "tags": {"addr:city": "Trento", "addr:country": "IT", "addr:housenumber": "70", "addr:postcode": "38122", "addr:street": "Corso Michelangelo Buonarroti", "name": "Prestabici", "service:bicycle:rental": "yes", "service:bicycle:repair": "yes", "shop": "bicycle"}}, "geometry": {"type": "Point", "coordinates": [11.1170977, 46.0714086]}}